DIYables_MicroPython_OLED/DIYables_MicroPython_OLED.py
DIYables_MicroPython_OLED/__init__.py
DIYables_MicroPython_OLED-0.1.1.dist-info/LICENSE
DIYables_MicroPython_OLED-0.1.1.dist-info/METADATA
DIYables_MicroPython_OLED-0.1.1.dist-info/WHEEL
DIYables_MicroPython_OLED-0.1.1.dist-info/top_level.txt
DIYables_MicroPython_OLED-0.1.1.dist-info/RECORD
